nextcloud_status/__init__.py
nextcloud_status/gh_emoji.json
nextcloud_status/nextcloud-status.py
nextcloud_status/nextcloud_status.py
nextcloud_status/status_gui.py
nextcloud_status-0.2.1.dist-info/LICENSE
nextcloud_status-0.2.1.dist-info/METADATA
nextcloud_status-0.2.1.dist-info/WHEEL
nextcloud_status-0.2.1.dist-info/entry_points.txt
nextcloud_status-0.2.1.dist-info/top_level.txt
nextcloud_status-0.2.1.dist-info/RECORD
