Metadata-Version: 2.1
Name: nextcloud-status
Version: 0.2.1
Summary: A CLI tool for updating NextCloud status
Home-page: https://github.com/coljac/nextcloud-status
Author: Colin Jacobs
Author-email: colin@coljac.net
License: MIT
Classifier: Programming Language :: Python :: 3
Classifier: License :: OSI Approved :: MIT License
Classifier: Operating System :: OS Independent
Requires-Python: >=3.7
License-File: LICENSE
Requires-Dist: requests >=2.25.1
Requires-Dist: typer >=0.12.3
